exudynGUI/__init__.py
exudynGUI/__main__.py
exudynGUI/_version.py
exudynGUI/main.py
exudynGUI/core/__init__.py
exudynGUI/core/debug.py
exudynGUI/core/extractModelStructure.py
exudynGUI/core/fieldMetadata.py
exudynGUI/core/fieldValidation.py
exudynGUI/core/generateCode.py
exudynGUI/core/graphicsUtils.py
exudynGUI/core/helpUtils.py
exudynGUI/core/modelManager.py
exudynGUI/core/outputDiscovery.py
exudynGUI/core/output_discovery_worker.py
exudynGUI/core/parameterHelp.py
exudynGUI/core/qtImports.py
exudynGUI/core/rendererState.py
exudynGUI/core/settingsComparison.py
exudynGUI/core/specialFields.py
exudynGUI/core/variableManager.py
exudynGUI/core/widgetFactory.py
exudynGUI/core/widgetUtils.py
exudynGUI/design/__init__.py
exudynGUI/design/assets/exudynLogo.png
exudynGUI/design/createItems/CartesianSpringDamper.png
exudynGUI/design/createItems/CoordinateConstraint.png
exudynGUI/design/createItems/DistanceConstraint.png
exudynGUI/design/createItems/DistanceSensor.png
exudynGUI/design/createItems/DistanceSensorGeometry.png
exudynGUI/design/createItems/Force.png
exudynGUI/design/createItems/GenericJoint.png
exudynGUI/design/createItems/Ground.png
exudynGUI/design/createItems/KinematicTree.png
exudynGUI/design/createItems/MassPoint.png
exudynGUI/design/createItems/PrismaticJoint.png
exudynGUI/design/createItems/RevoluteJoint.png
exudynGUI/design/createItems/RigidBody.png
exudynGUI/design/createItems/RigidBodySpringDamper.png
exudynGUI/design/createItems/RollingDisc.png
exudynGUI/design/createItems/RollingDiscPenalty.png
exudynGUI/design/createItems/SphereQuadContact.png
exudynGUI/design/createItems/SphereSphereContact.png
exudynGUI/design/createItems/SphereTriangleContact.png
exudynGUI/design/createItems/SphericalJoint.png
exudynGUI/design/createItems/SpringDamper.png
exudynGUI/design/createItems/Torque.png
exudynGUI/design/createItems/TorsionalSpringDamper.png
exudynGUI/design/legacyItems/Loads.png
exudynGUI/design/legacyItems/Markers.png
exudyngui-0.4.3.dist-info/licenses/LICENSE
exudyngui-0.4.3.dist-info/METADATA
exudyngui-0.4.3.dist-info/WHEEL
exudyngui-0.4.3.dist-info/entry_points.txt
exudyngui-0.4.3.dist-info/top_level.txt
exudyngui-0.4.3.dist-info/RECORD
