Metadata-Version: 2.4
Name: exudynGUI
Version: 0.4.3
Summary: A graphical user interface for Exudyn multibody simulation
Author-email: Michael Pieber <michael.pieber@uibk.ac.at>
Maintainer-email: Michael Pieber <michael.pieber@uibk.ac.at>
License-Expression: BSD-3-Clause
Project-URL: Homepage, https://github.com/MichaelUIBK/exudynGUI
Project-URL: Documentation, https://exudyn.readthedocs.io/
Project-URL: Repository, https://github.com/MichaelUIBK/exudynGUI
Project-URL: Bug Tracker, https://github.com/MichaelUIBK/exudynGUI/issues
Project-URL: Download, https://github.com/MichaelUIBK/exudynGUI/releases
Keywords: exudyn,multibody,simulation,gui,physics,engineering
Classifier: Development Status :: 3 - Alpha
Classifier: Intended Audience :: Science/Research
Classifier: Topic :: Scientific/Engineering :: Physics
Classifier: Topic :: Scientific/Engineering :: Mathematics
Classifier: Programming Language :: Python :: 3
Classifier: Programming Language :: Python :: 3.8
Classifier: Programming Language :: Python :: 3.9
Classifier: Programming Language :: Python :: 3.10
Classifier: Programming Language :: Python :: 3.11
Classifier: Operating System :: OS Independent
Requires-Python: >=3.8
License-File: LICENSE
Requires-Dist: PyQt5>=5.15.0
Requires-Dist: numpy>=1.20.0
Requires-Dist: PyMuPDF>=1.20.0
Requires-Dist: PyPDF2>=3.0.0
Requires-Dist: QScintilla>=2.14.0
Requires-Dist: jupyter-client>=7.0.0
Requires-Dist: qtconsole>=5.3.0
Requires-Dist: ipython>=7.0.0
Requires-Dist: networkx>=2.6.0
Provides-Extra: dev
Requires-Dist: black>=22.0.0; extra == "dev"
Requires-Dist: flake8>=4.0.0; extra == "dev"
Provides-Extra: flexible
Requires-Dist: ngsolve>=2022.1.0; extra == "flexible"
Requires-Dist: netgen>=6.2.0; extra == "flexible"
Provides-Extra: editor
Requires-Dist: QScintilla>=2.14.0; extra == "editor"
Dynamic: license-file
